{
    "task_name": {
        "_type": "choice",
        "_value": ["CoLA"]
    },
    "model_path": {
        "_type": "choice",
        "_value": ["models"]
    },
    "model_name": {
        "_type": "choice",
        "_value": ["roberta-large"]
    },
    "seed": {
        "_type": "randint",
        "_value": [0,10000]
    },
    "batch_size": {
        "_type": "choice",
        "_value": [16]
    },
    "epochs": {
        "_type": "choice",
        "_value": [5]
    },
    "adv_init_type": {
        "_type": "choice",
        "_value": ["zero, rand, randn"]
    },
    "adv_init_epsilon": {
        "_type": "quniform",
        "_value": [0.0001, 0.001, 0.0001]
    },
    "warm_up": {
        "_type": "choice",
        "_value": [0.1, 0.05]
    },
    "sampling_times_theta": {
        "_type": "choice",
        "_value": [10, 20]
    },
    "sampling_times_delta": {
        "_type": "choice",
        "_value": [10]
    },
    "sampling_step_theta": {
        "_type": "quniform",
        "_value": [0.00001, 0.001, 0.00001]
    },
    "sampling_step_delta": {
        "_type": "quniform",
        "_value": [0.00001, 0.001, 0.00001]
    },
    "sampling_noise_ratio": {
        "_type": "choice",
        "_value": [0.1, 0.01, 0.05]
    },
    "lambda_s": {
        "_type": "choice",
        "_value": [0.1, 1, 5]
    },
    "beta_s": {
        "_type": "quniform",
        "_value": [0.1, 0.9, 0.1]
    },
    "beta_p": {
        "_type": "quniform",
        "_value": [0.1, 0.9, 0.1]
    },
    "eval_times": {
        "_type": "choice",
        "_value": [10]
    },
    "predict": {
        "_type": "choice",
        "_value": ["True"]
    }
}